dbt_superset_lineage/.DS_Store
dbt_superset_lineage/__init__.py
dbt_superset_lineage/pull_dashboards.py
dbt_superset_lineage/push_descriptions.py
dbt_superset_lineage/superset_api.py
dbt_superset_lineage-0.3.3.dist-info/LICENSE.md
dbt_superset_lineage-0.3.3.dist-info/METADATA
dbt_superset_lineage-0.3.3.dist-info/WHEEL
dbt_superset_lineage-0.3.3.dist-info/entry_points.txt
dbt_superset_lineage-0.3.3.dist-info/RECORD
