Metadata-Version: 2.1
Name: dbt-superset-lineage
Version: 0.3.3
Summary: Make dbt docs and Apache Superset talk to one another
Home-page: https://github.com/slidoapp/dbt-superset-lineage
Author: Michal Kolacek
Author-email: mkolacek@slido.com
Requires-Python: >=3.8,<4.0
Classifier: Programming Language :: Python :: 3
Classifier: Programming Language :: Python :: 3.8
Classifier: Programming Language :: Python :: 3.9
Classifier: Programming Language :: Python :: 3.10
Classifier: Programming Language :: Python :: 3.11
Requires-Dist: Markdown (>=3.3.6,<4.0.0)
Requires-Dist: bs4 (>=0.0.1,<0.0.2)
Requires-Dist: pathlib (>=1.0.1,<2.0.0)
Requires-Dist: pytest (>=7.2.2,<8.0.0)
Requires-Dist: requests (>=2.26.0,<3.0.0)
Requires-Dist: ruamel.yaml (>=0.17.17,<0.18.0)
Requires-Dist: sqlfluff (>=1.4.1,<3.0.0)
Requires-Dist: typer (>=0.4.0,<0.5.0)
Project-URL: Repository, https://github.com/slidoapp/dbt-superset-lineage
